note_to_json/__init__.py
note_to_json/cli.py
note_to_json/parser.py
note_to_json/utils/__init__.py
note_to_json/utils/encoding.py
note_to_json-0.2.3.dist-info/licenses/LICENSE
note_to_json-0.2.3.dist-info/METADATA
note_to_json-0.2.3.dist-info/WHEEL
note_to_json-0.2.3.dist-info/entry_points.txt
note_to_json-0.2.3.dist-info/top_level.txt
note_to_json-0.2.3.dist-info/RECORD
