Metadata-Version: 2.4
Name: note-to-json
Version: 0.2.3
Summary: Convert Markdown or text files to structured JSON, offline.
Author: Note to JSON Team
License: MIT
Project-URL: Homepage, https://github.com/Mugiwara555343/note2json
Project-URL: Repository, https://github.com/Mugiwara555343/note2json
Project-URL: Issues, https://github.com/Mugiwara555343/note2json/issues
Keywords: markdown,json,cli,privacy,notes
Classifier: Development Status :: 4 - Beta
Classifier: Intended Audience :: Developers
Classifier: License :: OSI Approved :: MIT License
Classifier: Operating System :: OS Independent
Classifier: Programming Language :: Python :: 3
Classifier: Programming Language :: Python :: 3.10
Classifier: Programming Language :: Python :: 3.11
Classifier: Programming Language :: Python :: 3.12
Classifier: Topic :: Text Processing :: Markup
Classifier: Topic :: Software Development :: Libraries :: Python Modules
Requires-Python: >=3.10
License-File: LICENSE
Requires-Dist: jsonschema>=4.0.0
Requires-Dist: chardet>=5.0.0
Provides-Extra: dev
Requires-Dist: pytest>=7.0.0; extra == "dev"
Requires-Dist: pytest-cov>=4.0.0; extra == "dev"
Requires-Dist: pre-commit>=3.0.0; extra == "dev"
Requires-Dist: black>=24; extra == "dev"
Requires-Dist: ruff>=0.5; extra == "dev"
Provides-Extra: watch
Requires-Dist: watchdog>=3.0.0; extra == "watch"
Dynamic: license-file
